helloworld_test_5tgb/__init__.py
helloworld_test_5tgb-0.0.1.dist-info/METADATA
helloworld_test_5tgb-0.0.1.dist-info/WHEEL
helloworld_test_5tgb-0.0.1.dist-info/entry_points.txt
helloworld_test_5tgb-0.0.1.dist-info/top_level.txt
helloworld_test_5tgb-0.0.1.dist-info/RECORD
