Metadata-Version: 2.1
Name: helloworld-test-5tgb
Version: 0.0.1
Summary: helloworld
Home-page: UNKNOWN
Author: yiming
Author-email: test@test.com
License: UNKNOWN
Platform: UNKNOWN
